odoo/addons/sale_channel_search_engine_demo/README.rst
odoo/addons/sale_channel_search_engine_demo/__init__.py
odoo/addons/sale_channel_search_engine_demo/__manifest__.py
odoo/addons/sale_channel_search_engine_demo/demo/ir_exports_demo.xml
odoo/addons/sale_channel_search_engine_demo/demo/sale_channel_demo.xml
odoo/addons/sale_channel_search_engine_demo/demo/se_backend_demo.xml
odoo/addons/sale_channel_search_engine_demo/demo/se_index_config_demo.xml
odoo/addons/sale_channel_search_engine_demo/demo/se_index_demo.xml
odoo/addons/sale_channel_search_engine_demo/i18n/it.po
odoo/addons/sale_channel_search_engine_demo/i18n/sale_channel_search_engine_demo.pot
odoo/addons/sale_channel_search_engine_demo/readme/CONTRIBUTORS.rst
odoo/addons/sale_channel_search_engine_demo/readme/DESCRIPTION.rst
odoo/addons/sale_channel_search_engine_demo/static/description/icon.png
odoo/addons/sale_channel_search_engine_demo/static/description/index.html
odoo_addon_sale_channel_search_engine_demo-16.0.0.0.1.1.dist-info/METADATA
odoo_addon_sale_channel_search_engine_demo-16.0.0.0.1.1.dist-info/WHEEL
odoo_addon_sale_channel_search_engine_demo-16.0.0.0.1.1.dist-info/top_level.txt
odoo_addon_sale_channel_search_engine_demo-16.0.0.0.1.1.dist-info/RECORD
